__init__.py
layers_linter/__init__.py
layers_linter/analyzer.py
layers_linter/cli.py
layers_linter/config.py
layers_linter/flake8_plugin.py
layers_linter/imports.py
layers_linter/search_modules.py
layers_linter-3.2.2.dist-info/METADATA
layers_linter-3.2.2.dist-info/WHEEL
layers_linter-3.2.2.dist-info/entry_points.txt
layers_linter-3.2.2.dist-info/top_level.txt
layers_linter-3.2.2.dist-info/RECORD
