Metadata-Version: 2.4
Name: layers-linter
Version: 3.2.2
Summary: A static code analyzer that enforces architectural boundaries for layers and outher libraries
Project-URL: Homepage, https://github.com/pavelmaksimov/layers-linter
Project-URL: Bug Tracker, https://github.com/pavelmaksimov/layers-linter/issues
Requires-Python: >=3.11
Provides-Extra: flake8
Requires-Dist: flake8>=7.2.0; extra == "flake8"
